Metadata-Version: 2.1
Name: transposonmapper
Version: 1.1.5
Summary: A libray for processing sequencing data for SAturated Transposon Analysis in Yeast (SATAY)
Home-page: https://github.com/SATAY-LL/Transposonmapper
Author: Liedewij Laan Lab
Author-email: L.M.InigoDeLaCruz@tudelft.nl
License: Apache Software License 2.0
Platform: UNKNOWN
Classifier: Development Status :: 4 - Beta
Classifier: Intended Audience :: Education
Classifier: Intended Audience :: Science/Research
Classifier: Intended Audience :: Developers
Classifier: License :: OSI Approved :: Apache Software License
Classifier: Natural Language :: English
Classifier: Programming Language :: Python :: 3.8
Classifier: Programming Language :: Unix Shell
License-File: LICENSE
Requires-Dist: numpy
Requires-Dist: matplotlib
Requires-Dist: scipy
Requires-Dist: pandas
Provides-Extra: dev
Requires-Dist: bump2version ; extra == 'dev'
Requires-Dist: mock ; extra == 'dev'
Requires-Dist: pysam ; extra == 'dev'
Requires-Dist: pytest ; extra == 'dev'
Requires-Dist: pytest-cov ; extra == 'dev'
Requires-Dist: jupyter-book (>=0.7.0) ; extra == 'dev'
Requires-Dist: sphinx-click ; extra == 'dev'
Requires-Dist: sphinx-tabs ; extra == 'dev'
Requires-Dist: sphinxext-rediraffe ; extra == 'dev'
Requires-Dist: sphinx-inline-tabs ; extra == 'dev'
Requires-Dist: ghp-import ; extra == 'dev'
Provides-Extra: linux
Requires-Dist: pysam ; extra == 'linux'
